toslack/__init__.py
toslack/py.typed
toslack/slack_client.py
toslack/slack_message.py
toslack-0.1.0.dist-info/LICENSE
toslack-0.1.0.dist-info/METADATA
toslack-0.1.0.dist-info/WHEEL
toslack-0.1.0.dist-info/top_level.txt
toslack-0.1.0.dist-info/RECORD
