Metadata-Version: 2.1
Name: toslack
Version: 0.1.0
Summary: Python API and CLI for sending message in Slack
Author-email: HowieMen <howiemen@gmail.com>
License: The MIT License (MIT)
Project-URL: Homepage, https://github.com/HowieMen/toslack
Project-URL: Bug Tracker, https://github.com/HowieMen/toslack/issues
Keywords: slack,slack-api,chat,chatbot
Classifier: Intended Audience :: Developers
Classifier: Topic :: Communications :: Chat
Classifier: Topic :: System :: Networking
Classifier: Topic :: Office/Business
Classifier: License :: OSI Approved :: MIT License
Classifier: Programming Language :: Python
Classifier: Programming Language :: Python :: 3 :: Only
Classifier: Operating System :: OS Independent
Requires-Python: >=3.6
License-File: LICENSE
Requires-Dist: slack-sdk >=3.31.0
